CHANGELOG.md
LICENSE
README.md
src/cmu-rpa-sistem/__init__.py
src/cmu-rpa-sistem/core.py
src/cmu-rpa-sistem/py.typed
cmu_rpa_sistem-0.1.0.dist-info/METADATA
cmu_rpa_sistem-0.1.0.dist-info/WHEEL
cmu_rpa_sistem-0.1.0.dist-info/licenses/LICENSE
cmu_rpa_sistem-0.1.0.dist-info/RECORD
