Metadata-Version: 2.4
Name: cmu-rpa-sistem
Version: 0.1.0
Summary: Uma biblioteca de exemplo com layout src, tipos e CLI.
Project-URL: Homepage, https://github.com/sanziolopes-cmu/RPA-MODEL
Project-URL: Documentation, https://github.com/sanziolopes-cmu/RPA-MODEL/README.md
Author-email: Sanzio Dinelli <sanzio.magalhae@gmail.com>
License: GNU GENERAL PUBLIC LICENSE
License-File: LICENSE
Keywords: exemplo,packaging,pypi
Classifier: License :: OSI Approved :: MIT License
Classifier: Programming Language :: Python :: 3
Classifier: Programming Language :: Python :: 3 :: Only
Classifier: Typing :: Typed
Requires-Python: >=3.9
